{
    "title": "06. Fn + keys  ——  others",
    "rules": [
        {
            "description": "06. Fn + keys  ——  others",
            "manipulators": [
                {
                    "from": {
                        "key_code": "tab",
                        "modifiers": {
                            "mandatory": [
                                "fn"
                            ],
                            "optional": [
                                "any"
                            ]
                        }
                    },
                    "to": [
                        {
                            "key_code": "space"
                        },
                        {
                            "key_code": "space"
                        },
                        {
                            "key_code": "space"
                        },
                        {
                            "key_code": "space"
                        }
                    ],
                    "type": "basic"
                },
                {
                    "from": {
                        "key_code": "u",
                        "modifiers": {
                            "mandatory": [
                                "fn"
                            ],
                            "optional": [
                                "any"
                            ]
                        }
                    },
                    "to": [
                        {
                            "key_code": "caps_lock"
                        }
                    ],
                    "type": "basic"
                },
                {
                    "from": {
                        "key_code": "i",
                        "modifiers": {
                            "mandatory": [
                                "fn"
                            ],
                            "optional": [
                                "any"
                            ]
                        }
                    },
                    "to": [
                        {
                            "key_code": "f20"
                        }
                    ],
                    "type": "basic"
                },
                {
                    "from": {
                        "key_code": "o",
                        "modifiers": {
                            "mandatory": [
                                "fn"
                            ],
                            "optional": [
                                "any"
                            ]
                        }
                    },
                    "to": [
                        {
                            "key_code": "f13"
                        }
                    ],
                    "type": "basic"
                },
                {
                    "from": {
                        "key_code": "p",
                        "modifiers": {
                            "mandatory": [
                                "fn"
                            ],
                            "optional": [
                                "any"
                            ]
                        }
                    },
                    "to": [
                        {
                            "key_code": "f18"
                        }
                    ],
                    "type": "basic"
                },
                {
                    "from": {
                        "key_code": "return_or_enter",
                        "modifiers": {
                            "mandatory": [
                                "fn"
                            ],
                            "optional": [
                                "any"
                            ]
                        }
                    },
                    "to": [
                        {
                            "key_code": "f19"
                        }
                    ],
                    "type": "basic"
                }
            ]
        }
    ]
}
